mexc/__init__.py
mexc/ccxt/__init__.py
mexc/ccxt/mexc.py
mexc/ccxt/abstract/mexc.py
mexc/ccxt/async_support/__init__.py
mexc/ccxt/async_support/mexc.py
mexc/ccxt/async_support/base/__init__.py
mexc/ccxt/async_support/base/exchange.py
mexc/ccxt/async_support/base/throttler.py
mexc/ccxt/async_support/base/ws/__init__.py
mexc/ccxt/async_support/base/ws/cache.py
mexc/ccxt/async_support/base/ws/client.py
mexc/ccxt/async_support/base/ws/functions.py
mexc/ccxt/async_support/base/ws/future.py
mexc/ccxt/async_support/base/ws/order_book.py
mexc/ccxt/async_support/base/ws/order_book_side.py
mexc/ccxt/base/__init__.py
mexc/ccxt/base/decimal_to_precision.py
mexc/ccxt/base/errors.py
mexc/ccxt/base/exchange.py
mexc/ccxt/base/precise.py
mexc/ccxt/base/types.py
mexc/ccxt/pro/__init__.py
mexc/ccxt/pro/mexc.py
mexc/ccxt/static_dependencies/README.md
mexc/ccxt/static_dependencies/__init__.py
mexc/ccxt/static_dependencies/bip/__init__.py
mexc/ccxt/static_dependencies/bip/addr/P2PKH_addr.py
mexc/ccxt/static_dependencies/bip/addr/__init__.py
mexc/ccxt/static_dependencies/bip/addr/addr_dec_utils.py
mexc/ccxt/static_dependencies/bip/addr/addr_key_validator.py
mexc/ccxt/static_dependencies/bip/addr/iaddr_decoder.py
mexc/ccxt/static_dependencies/bip/addr/iaddr_encoder.py
mexc/ccxt/static_dependencies/bip/base58/__init__.py
mexc/ccxt/static_dependencies/bip/base58/base58.py
mexc/ccxt/static_dependencies/bip/base58/base58_ex.py
mexc/ccxt/static_dependencies/bip/base58/base58_xmr.py
mexc/ccxt/static_dependencies/bip/bech32/__init__.py
mexc/ccxt/static_dependencies/bip/bech32/bch_bech32.py
mexc/ccxt/static_dependencies/bip/bech32/bech32.py
mexc/ccxt/static_dependencies/bip/bech32/bech32_base.py
mexc/ccxt/static_dependencies/bip/bech32/bech32_ex.py
mexc/ccxt/static_dependencies/bip/bech32/segwit_bech32.py
mexc/ccxt/static_dependencies/bip/bip32/__init__.py
mexc/ccxt/static_dependencies/bip/bip32/bip32_const.py
mexc/ccxt/static_dependencies/bip/bip32/bip32_ex.py
mexc_exchange_api-0.0.121.dist-info/METADATA
mexc_exchange_api-0.0.121.dist-info/WHEEL
mexc_exchange_api-0.0.121.dist-info/RECORD
